farbfeld.py
farbfeld-0.2.2.dist-info/LICENSE.md
farbfeld-0.2.2.dist-info/METADATA
farbfeld-0.2.2.dist-info/WHEEL
farbfeld-0.2.2.dist-info/top_level.txt
farbfeld-0.2.2.dist-info/RECORD
