Metadata-Version: 2.1
Name: farbfeld
Version: 0.2.2
Summary: Library for reading/writing farbfeld images.
Home-page: https://github.com/jmp/farbfeld
Author: Jarkko Piiroinen
Author-email: jmp@python.mail.kapsi.fi
License: MIT
Platform: any
Classifier: Programming Language :: Python :: 3
Classifier: License :: OSI Approved :: MIT License
Classifier: Operating System :: OS Independent
Classifier: Topic :: Multimedia :: Graphics
Classifier: Intended Audience :: Developers
